{
  "type": "Program",
  "body": [
    {
      "type": "ExpressionStatement",
      "expression": {
        "type": "Literal",
        "value": "use strict",
        "raw": "'use strict'",
        "range": [
          0,
          12
        ],
        "loc": {
          "start": {
            "line": 1,
            "column": 0
          },
          "end": {
            "line": 1,
            "column": 12
          }
        }
      },
      "range": [
        0,
        14
      ],
      "loc": {
        "start": {
          "line": 1,
          "column": 0
        },
        "end": {
          "line": 3,
          "column": 0
        }
      }
    },
    {
      "type": "ImportDeclaration",
      "specifiers": [
        {
          "type": "ImportDefaultSpecifier",
          "local": {
            "type": "Identifier",
            "name": "Renderer",
            "range": [
              21,
              29
            ],
            "loc": {
              "start": {
                "line": 3,
                "column": 7
              },
              "end": {
                "line": 3,
                "column": 15
              }
            }
          },
          "range": [
            21,
            29
          ],
          "loc": {
            "start": {
              "line": 3,
              "column": 7
            },
            "end": {
              "line": 3,
              "column": 15
            }
          }
        }
      ],
      "source": {
        "type": "Literal",
        "value": "../../base/Renderer",
        "raw": "'../../base/Renderer'",
        "range": [
          35,
          56
        ],
        "loc": {
          "start": {
            "line": 3,
            "column": 21
          },
          "end": {
            "line": 3,
            "column": 42
          }
        },
        "trailingComments": [
          {
            "type": "Block",
            "value": "*\n * ToonRenderer class\n * @access public\n ",
            "range": [
              58,
              105
            ],
            "loc": {
              "start": {
                "line": 5,
                "column": 0
              },
              "end": {
                "line": 8,
                "column": 3
              }
            }
          }
        ]
      },
      "range": [
        14,
        106
      ],
      "loc": {
        "start": {
          "line": 3,
          "column": 0
        },
        "end": {
          "line": 9,
          "column": 0
        }
      }
    },
    {
      "type": "ExportDefaultDeclaration",
      "declaration": {
        "type": "ClassDeclaration",
        "id": {
          "type": "Identifier",
          "name": "ToonRenderer",
          "range": [
            127,
            139
          ],
          "loc": {
            "start": {
              "line": 9,
              "column": 21
            },
            "end": {
              "line": 9,
              "column": 33
            }
          }
        },
        "superClass": {
          "type": "Identifier",
          "name": "Renderer",
          "range": [
            148,
            156
          ],
          "loc": {
            "start": {
              "line": 9,
              "column": 42
            },
            "end": {
              "line": 9,
              "column": 50
            }
          }
        },
        "body": {
          "type": "ClassBody",
          "body": [
            {
              "type": "MethodDefinition",
              "key": {
                "type": "Identifier",
                "name": "constructor",
                "range": [
                  298,
                  309
                ],
                "loc": {
                  "start": {
                    "line": 17,
                    "column": 2
                  },
                  "end": {
                    "line": 17,
                    "column": 13
                  }
                }
              },
              "value": {
                "type": "FunctionExpression",
                "id": null,
                "params": [
                  {
                    "type": "Identifier",
                    "name": "gl",
                    "range": [
                      310,
                      312
                    ],
                    "loc": {
                      "start": {
                        "line": 17,
                        "column": 14
                      },
                      "end": {
                        "line": 17,
                        "column": 16
                      }
                    }
                  },
                  {
                    "type": "Identifier",
                    "name": "camera",
                    "range": [
                      314,
                      320
                    ],
                    "loc": {
                      "start": {
                        "line": 17,
                        "column": 18
                      },
                      "end": {
                        "line": 17,
                        "column": 24
                      }
                    }
                  }
                ],
                "body": {
                  "type": "BlockStatement",
                  "body": [
                    {
                      "type": "ExpressionStatement",
                      "expression": {
                        "type": "CallExpression",
                        "callee": {
                          "type": "Super",
                          "range": [
                            328,
                            333
                          ],
                          "loc": {
                            "start": {
                              "line": 18,
                              "column": 4
                            },
                            "end": {
                              "line": 18,
                              "column": 9
                            }
                          }
                        },
                        "arguments": [
                          {
                            "type": "Identifier",
                            "name": "gl",
                            "range": [
                              334,
                              336
                            ],
                            "loc": {
                              "start": {
                                "line": 18,
                                "column": 10
                              },
                              "end": {
                                "line": 18,
                                "column": 12
                              }
                            }
                          },
                          {
                            "type": "Identifier",
                            "name": "camera",
                            "range": [
                              338,
                              344
                            ],
                            "loc": {
                              "start": {
                                "line": 18,
                                "column": 14
                              },
                              "end": {
                                "line": 18,
                                "column": 20
                              }
                            }
                          }
                        ],
                        "range": [
                          328,
                          345
                        ],
                        "loc": {
                          "start": {
                            "line": 18,
                            "column": 4
                          },
                          "end": {
                            "line": 18,
                            "column": 21
                          }
                        }
                      },
                      "range": [
                        328,
                        348
                      ],
                      "loc": {
                        "start": {
                          "line": 18,
                          "column": 4
                        },
                        "end": {
                          "line": 19,
                          "column": 2
                        }
                      }
                    }
                  ],
                  "range": [
                    322,
                    349
                  ],
                  "loc": {
                    "start": {
                      "line": 17,
                      "column": 26
                    },
                    "end": {
                      "line": 19,
                      "column": 3
                    }
                  }
                },
                "generator": false,
                "expression": false,
                "range": [
                  309,
                  349
                ],
                "loc": {
                  "start": {
                    "line": 17,
                    "column": 13
                  },
                  "end": {
                    "line": 19,
                    "column": 3
                  }
                }
              },
              "kind": "constructor",
              "computed": false,
              "range": [
                298,
                349
              ],
              "loc": {
                "start": {
                  "line": 17,
                  "column": 2
                },
                "end": {
                  "line": 19,
                  "column": 3
                }
              },
              "leadingComments": [
                {
                  "type": "Block",
                  "value": "*\n   * constructor\n   * @access public\n   * @param {WebglContextRenderer} gl -\n   * @param {Camera} camera -\n   * @constructor\n   ",
                  "range": [
                    161,
                    295
                  ],
                  "loc": {
                    "start": {
                      "line": 10,
                      "column": 2
                    },
                    "end": {
                      "line": 16,
                      "column": 5
                    }
                  }
                }
              ],
              "static": false
            },
            {
              "type": "MethodDefinition",
              "key": {
                "type": "Identifier",
                "name": "_vertexShaderName",
                "range": [
                  357,
                  374
                ],
                "loc": {
                  "start": {
                    "line": 21,
                    "column": 6
                  },
                  "end": {
                    "line": 21,
                    "column": 23
                  }
                }
              },
              "value": {
                "type": "FunctionExpression",
                "id": null,
                "params": [],
                "body": {
                  "type": "BlockStatement",
                  "body": [
                    {
                      "type": "ReturnStatement",
                      "argument": {
                        "type": "Literal",
                        "value": "ToonVertexShader",
                        "raw": "'ToonVertexShader'",
                        "range": [
                          390,
                          408
                        ],
                        "loc": {
                          "start": {
                            "line": 22,
                            "column": 11
                          },
                          "end": {
                            "line": 22,
                            "column": 29
                          }
                        }
                      },
                      "range": [
                        383,
                        411
                      ],
                      "loc": {
                        "start": {
                          "line": 22,
                          "column": 4
                        },
                        "end": {
                          "line": 23,
                          "column": 2
                        }
                      }
                    }
                  ],
                  "range": [
                    377,
                    412
                  ],
                  "loc": {
                    "start": {
                      "line": 21,
                      "column": 26
                    },
                    "end": {
                      "line": 23,
                      "column": 3
                    }
                  }
                },
                "generator": false,
                "expression": false,
                "range": [
                  374,
                  412
                ],
                "loc": {
                  "start": {
                    "line": 21,
                    "column": 23
                  },
                  "end": {
                    "line": 23,
                    "column": 3
                  }
                }
              },
              "kind": "get",
              "computed": false,
              "range": [
                353,
                412
              ],
              "loc": {
                "start": {
                  "line": 21,
                  "column": 2
                },
                "end": {
                  "line": 23,
                  "column": 3
                }
              },
              "static": false
            },
            {
              "type": "MethodDefinition",
              "key": {
                "type": "Identifier",
                "name": "_fragmentShaderName",
                "range": [
                  420,
                  439
                ],
                "loc": {
                  "start": {
                    "line": 25,
                    "column": 6
                  },
                  "end": {
                    "line": 25,
                    "column": 25
                  }
                }
              },
              "value": {
                "type": "FunctionExpression",
                "id": null,
                "params": [],
                "body": {
                  "type": "BlockStatement",
                  "body": [
                    {
                      "type": "ReturnStatement",
                      "argument": {
                        "type": "Literal",
                        "value": "ToonFragmentShader",
                        "raw": "'ToonFragmentShader'",
                        "range": [
                          455,
                          475
                        ],
                        "loc": {
                          "start": {
                            "line": 26,
                            "column": 11
                          },
                          "end": {
                            "line": 26,
                            "column": 31
                          }
                        }
                      },
                      "range": [
                        448,
                        478
                      ],
                      "loc": {
                        "start": {
                          "line": 26,
                          "column": 4
                        },
                        "end": {
                          "line": 27,
                          "column": 2
                        }
                      }
                    }
                  ],
                  "range": [
                    442,
                    479
                  ],
                  "loc": {
                    "start": {
                      "line": 25,
                      "column": 28
                    },
                    "end": {
                      "line": 27,
                      "column": 3
                    }
                  }
                },
                "generator": false,
                "expression": false,
                "range": [
                  439,
                  479
                ],
                "loc": {
                  "start": {
                    "line": 25,
                    "column": 25
                  },
                  "end": {
                    "line": 27,
                    "column": 3
                  }
                }
              },
              "kind": "get",
              "computed": false,
              "range": [
                416,
                479
              ],
              "loc": {
                "start": {
                  "line": 25,
                  "column": 2
                },
                "end": {
                  "line": 27,
                  "column": 3
                }
              },
              "static": false
            }
          ],
          "range": [
            157,
            481
          ],
          "loc": {
            "start": {
              "line": 9,
              "column": 51
            },
            "end": {
              "line": 28,
              "column": 1
            }
          }
        },
        "range": [
          121,
          481
        ],
        "loc": {
          "start": {
            "line": 9,
            "column": 15
          },
          "end": {
            "line": 28,
            "column": 1
          }
        },
        "leadingComments": [
          {
            "type": "Block",
            "value": "*\n * ToonRenderer class\n * @access public\n ",
            "range": [
              58,
              105
            ],
            "loc": {
              "start": {
                "line": 5,
                "column": 0
              },
              "end": {
                "line": 8,
                "column": 3
              }
            }
          }
        ],
        "trailingComments": []
      },
      "range": [
        106,
        481
      ],
      "loc": {
        "start": {
          "line": 9,
          "column": 0
        },
        "end": {
          "line": 28,
          "column": 1
        }
      },
      "leadingComments": [
        {
          "type": "Block",
          "value": "*\n * ToonRenderer class\n * @access public\n ",
          "range": [
            58,
            105
          ],
          "loc": {
            "start": {
              "line": 5,
              "column": 0
            },
            "end": {
              "line": 8,
              "column": 3
            }
          }
        }
      ]
    }
  ],
  "sourceType": "module",
  "range": [
    0,
    481
  ],
  "loc": {
    "start": {
      "line": 1,
      "column": 0
    },
    "end": {
      "line": 28,
      "column": 1
    }
  },
  "comments": [
    {
      "type": "Block",
      "value": "*\n * ToonRenderer class\n * @access public\n ",
      "range": [
        58,
        105
      ],
      "loc": {
        "start": {
          "line": 5,
          "column": 0
        },
        "end": {
          "line": 8,
          "column": 3
        }
      }
    },
    {
      "type": "Block",
      "value": "*\n   * constructor\n   * @access public\n   * @param {WebglContextRenderer} gl -\n   * @param {Camera} camera -\n   * @constructor\n   ",
      "range": [
        161,
        295
      ],
      "loc": {
        "start": {
          "line": 10,
          "column": 2
        },
        "end": {
          "line": 16,
          "column": 5
        }
      }
    }
  ]
}